scoredb/__init__.py
scoredb/client/__init__.py
scoredb/client/_baseapi.py
scoredb/client/_pagination.py
scoredb/client/studentdb.py
scoredb/client/users.py
scoredb/models/__init__.py
scoredb/models/class_.py
scoredb/models/grade.py
scoredb/models/student.py
scoredb/models/user.py
scoredb_sdk-0.1.4.dist-info/LICENSE
scoredb_sdk-0.1.4.dist-info/WHEEL
scoredb_sdk-0.1.4.dist-info/METADATA
scoredb_sdk-0.1.4.dist-info/RECORD
