Metadata-Version: 2.1
Name: scoredb-sdk
Version: 0.1.4
Summary: Python SDK of the ScoreDB v3 API Server.
Home-page: https://github.com/ScoreDB/sdk-python.git
License: GPL-3.0-or-later
Author: JingBh
Author-email: jingbohao@yeah.net
Requires-Python: >=3.7,<4.0
Classifier: License :: OSI Approved :: GNU General Public License v3 or later (GPLv3+)
Classifier: Programming Language :: Python :: 3
Classifier: Programming Language :: Python :: 3.7
Classifier: Programming Language :: Python :: 3.8
Classifier: Programming Language :: Python :: 3.9
Requires-Dist: requests (>=2.25.1,<3.0.0)
Project-URL: Repository, https://github.com/ScoreDB/sdk-python.git
